<?xml version="1.0"?>
<ArrayOfStation xmlns:xsi="http://www.w3.org/2001/XMLSchema-instance" xmlns:xsd="http://www.w3.org/2001/XMLSchema">
  <Station>
    <Id>5925</Id>
    <Name>Station0</Name>
    <Longitude>35.13359402429014</Longitude>
    <Latitude>31.798765005869214</Latitude>
    <ChargeSlots>10</ChargeSlots>
    <IsActive>true</IsActive>
  </Station>
  <Station>
    <Id>7701</Id>
    <Name>Station1</Name>
    <Longitude>35.23599275803938</Longitude>
    <Latitude>31.722527727588325</Latitude>
    <ChargeSlots>10</ChargeSlots>
    <IsActive>true</IsActive>
  </Station>
  <Station>
    <Id>7404</Id>
    <Name>Station2</Name>
    <Longitude>35.217272832951174</Longitude>
    <Latitude>31.718182063763113</Latitude>
    <ChargeSlots>6</ChargeSlots>
    <IsActive>true</IsActive>
  </Station>
  <Station>
    <Id>5107</Id>
    <Name>Station38888</Name>
    <Longitude>35.26045068854487</Longitude>
    <Latitude>31.812343870155672</Latitude>
    <ChargeSlots>7</ChargeSlots>
    <IsActive>false</IsActive>
  </Station>
  <Station>
    <Id>2196</Id>
    <Name>Station400</Name>
    <Longitude>35.23252203144716</Longitude>
    <Latitude>31.807417248518867</Latitude>
    <ChargeSlots>8</ChargeSlots>
    <IsActive>true</IsActive>
  </Station>
  <Station>
    <Id>9160</Id>
    <Name>Station5</Name>
    <Longitude>35.14571459509698</Longitude>
    <Latitude>31.84110697886958</Latitude>
    <ChargeSlots>7</ChargeSlots>
    <IsActive>true</IsActive>
  </Station>
  <Station>
    <Id>2169</Id>
    <Name>Station60</Name>
    <Longitude>35.23848521427181</Longitude>
    <Latitude>31.717330410991483</Latitude>
    <ChargeSlots>5</ChargeSlots>
    <IsActive>true</IsActive>
  </Station>
  <Station>
    <Id>5573</Id>
    <Name>Station7</Name>
    <Longitude>35.155645722828645</Longitude>
    <Latitude>31.721319642672928</Latitude>
    <ChargeSlots>9</ChargeSlots>
    <IsActive>false</IsActive>
  </Station>
  <Station>
    <Id>6799</Id>
    <Name>Station8</Name>
    <Longitude>35.21281736731195</Longitude>
    <Latitude>31.781636731271462</Latitude>
    <ChargeSlots>9</ChargeSlots>
    <IsActive>false</IsActive>
  </Station>
  <Station>
    <Id>9968</Id>
    <Name>Station9</Name>
    <Longitude>35.15230873453073</Longitude>
    <Latitude>31.865964136815613</Latitude>
    <ChargeSlots>10</ChargeSlots>
    <IsActive>true</IsActive>
  </Station>
  <Station>
    <Id>9139</Id>
    <Name>Station10</Name>
    <Longitude>35.22593698218741</Longitude>
    <Latitude>31.734192273129796</Latitude>
    <ChargeSlots>7</ChargeSlots>
    <IsActive>false</IsActive>
  </Station>
  <Station>
    <Id>3517</Id>
    <Name>Station11</Name>
    <Longitude>35.263434516342095</Longitude>
    <Latitude>31.82912725886755</Latitude>
    <ChargeSlots>10</ChargeSlots>
    <IsActive>true</IsActive>
  </Station>
  <Station>
    <Id>1769</Id>
    <Name>Station12</Name>
    <Longitude>35.29036759286671</Longitude>
    <Latitude>31.77468873470774</Latitude>
    <ChargeSlots>7</ChargeSlots>
    <IsActive>true</IsActive>
  </Station>
  <Station>
    <Id>9122</Id>
    <Name>Station13</Name>
    <Longitude>35.1354101313443</Longitude>
    <Latitude>31.81073672022239</Latitude>
    <ChargeSlots>10</ChargeSlots>
    <IsActive>true</IsActive>
  </Station>
  <Station>
    <Id>3387</Id>
    <Name>Station14</Name>
    <Longitude>35.25329838299812</Longitude>
    <Latitude>31.841996759056112</Latitude>
    <ChargeSlots>8</ChargeSlots>
    <IsActive>true</IsActive>
  </Station>
  <Station>
    <Id>4781</Id>
    <Name>Station15</Name>
    <Longitude>35.1717334907836</Longitude>
    <Latitude>31.82997764764818</Latitude>
    <ChargeSlots>8</ChargeSlots>
    <IsActive>true</IsActive>
  </Station>
  <Station>
    <Id>8314</Id>
    <Name>Station16</Name>
    <Longitude>35.22255334282413</Longitude>
    <Latitude>31.870157596361896</Latitude>
    <ChargeSlots>5</ChargeSlots>
    <IsActive>true</IsActive>
  </Station>
  <Station>
    <Id>9978</Id>
    <Name>Station17</Name>
    <Longitude>35.12182607726279</Longitude>
    <Latitude>31.719767976654584</Latitude>
    <ChargeSlots>6</ChargeSlots>
    <IsActive>true</IsActive>
  </Station>
  <Station>
    <Id>3479</Id>
    <Name>Station18</Name>
    <Longitude>35.25096879589882</Longitude>
    <Latitude>31.86424619376857</Latitude>
    <ChargeSlots>9</ChargeSlots>
    <IsActive>true</IsActive>
  </Station>
  <Station>
    <Id>1682</Id>
    <Name>Station19</Name>
    <Longitude>35.13564935765958</Longitude>
    <Latitude>31.876958308078795</Latitude>
    <ChargeSlots>7</ChargeSlots>
    <IsActive>true</IsActive>
  </Station>
  <Station>
    <Id>3425</Id>
    <Name>Station20</Name>
    <Longitude>35.28892292025915</Longitude>
    <Latitude>31.850497392821357</Latitude>
    <ChargeSlots>5</ChargeSlots>
    <IsActive>true</IsActive>
  </Station>
  <Station>
    <Id>2392</Id>
    <Name>Station21</Name>
    <Longitude>35.26662365997519</Longitude>
    <Latitude>31.856783154214163</Latitude>
    <ChargeSlots>5</ChargeSlots>
    <IsActive>true</IsActive>
  </Station>
  <Station>
    <Id>3080</Id>
    <Name>Station22</Name>
    <Longitude>35.18763230111806</Longitude>
    <Latitude>31.84446957285724</Latitude>
    <ChargeSlots>6</ChargeSlots>
    <IsActive>true</IsActive>
  </Station>
  <Station>
    <Id>1569</Id>
    <Name>Station23</Name>
    <Longitude>35.184233324362076</Longitude>
    <Latitude>31.820718454067</Latitude>
    <ChargeSlots>7</ChargeSlots>
    <IsActive>true</IsActive>
  </Station>
  <Station>
    <Id>8310</Id>
    <Name>Station24</Name>
    <Longitude>35.20621994608371</Longitude>
    <Latitude>31.704937886821543</Latitude>
    <ChargeSlots>7</ChargeSlots>
    <IsActive>true</IsActive>
  </Station>
  <Station>
    <Id>1295</Id>
    <Name>Station25</Name>
    <Longitude>35.28846131860673</Longitude>
    <Latitude>31.85379551144028</Latitude>
    <ChargeSlots>10</ChargeSlots>
    <IsActive>true</IsActive>
  </Station>
  <Station>
    <Id>3378</Id>
    <Name>Station26</Name>
    <Longitude>35.143754054626335</Longitude>
    <Latitude>31.829748474028776</Latitude>
    <ChargeSlots>5</ChargeSlots>
    <IsActive>true</IsActive>
  </Station>
  <Station>
    <Id>8189</Id>
    <Name>Station27</Name>
    <Longitude>35.25317779777254</Longitude>
    <Latitude>31.788269059214866</Latitude>
    <ChargeSlots>8</ChargeSlots>
    <IsActive>true</IsActive>
  </Station>
  <Station>
    <Id>5785</Id>
    <Name>Station28</Name>
    <Longitude>35.17769438581434</Longitude>
    <Latitude>31.75643306060528</Latitude>
    <ChargeSlots>9</ChargeSlots>
    <IsActive>true</IsActive>
  </Station>
  <Station>
    <Id>7347</Id>
    <Name>Station29</Name>
    <Longitude>35.190047045559645</Longitude>
    <Latitude>31.744783369472614</Latitude>
    <ChargeSlots>5</ChargeSlots>
    <IsActive>true</IsActive>
  </Station>
  <Station>
    <Id>1159</Id>
    <Name>Station30</Name>
    <Longitude>35.26341240497465</Longitude>
    <Latitude>31.804412129011197</Latitude>
    <ChargeSlots>6</ChargeSlots>
    <IsActive>true</IsActive>
  </Station>
  <Station>
    <Id>6946</Id>
    <Name>Station31</Name>
    <Longitude>35.147953365020435</Longitude>
    <Latitude>31.864515534771847</Latitude>
    <ChargeSlots>9</ChargeSlots>
    <IsActive>true</IsActive>
  </Station>
  <Station>
    <Id>4600</Id>
    <Name>Station32</Name>
    <Longitude>35.284682289783234</Longitude>
    <Latitude>31.80007607941519</Latitude>
    <ChargeSlots>5</ChargeSlots>
    <IsActive>true</IsActive>
  </Station>
  <Station>
    <Id>4183</Id>
    <Name>Station33</Name>
    <Longitude>35.19029140634942</Longitude>
    <Latitude>31.849859046447026</Latitude>
    <ChargeSlots>8</ChargeSlots>
    <IsActive>true</IsActive>
  </Station>
  <Station>
    <Id>8291</Id>
    <Name>Station34</Name>
    <Longitude>35.27408746386603</Longitude>
    <Latitude>31.891598706781675</Latitude>
    <ChargeSlots>8</ChargeSlots>
    <IsActive>true</IsActive>
  </Station>
  <Station>
    <Id>6086</Id>
    <Name>Station35</Name>
    <Longitude>35.15837328948936</Longitude>
    <Latitude>31.850378277129668</Latitude>
    <ChargeSlots>9</ChargeSlots>
    <IsActive>true</IsActive>
  </Station>
  <Station>
    <Id>9608</Id>
    <Name>Station36</Name>
    <Longitude>35.25096314109441</Longitude>
    <Latitude>31.711540198424615</Latitude>
    <ChargeSlots>9</ChargeSlots>
    <IsActive>true</IsActive>
  </Station>
  <Station>
    <Id>2936</Id>
    <Name>Station37</Name>
    <Longitude>35.209837989094595</Longitude>
    <Latitude>31.850688203866913</Latitude>
    <ChargeSlots>8</ChargeSlots>
    <IsActive>true</IsActive>
  </Station>
  <Station>
    <Id>6170</Id>
    <Name>Station38</Name>
    <Longitude>35.18225637482585</Longitude>
    <Latitude>31.800466759363406</Latitude>
    <ChargeSlots>8</ChargeSlots>
    <IsActive>true</IsActive>
  </Station>
  <Station>
    <Id>9567</Id>
    <Name>Station39</Name>
    <Longitude>35.165188537940935</Longitude>
    <Latitude>31.83340438862024</Latitude>
    <ChargeSlots>7</ChargeSlots>
    <IsActive>true</IsActive>
  </Station>
  <Station>
    <Id>4680</Id>
    <Name>Station40</Name>
    <Longitude>35.23623251343902</Longitude>
    <Latitude>31.809363994705194</Latitude>
    <ChargeSlots>6</ChargeSlots>
    <IsActive>true</IsActive>
  </Station>
  <Station>
    <Id>5661</Id>
    <Name>Station41</Name>
    <Longitude>35.105353740698355</Longitude>
    <Latitude>31.842945687911914</Latitude>
    <ChargeSlots>9</ChargeSlots>
    <IsActive>true</IsActive>
  </Station>
  <Station>
    <Id>8476</Id>
    <Name>Station42</Name>
    <Longitude>35.27150904628053</Longitude>
    <Latitude>31.877594002605225</Latitude>
    <ChargeSlots>9</ChargeSlots>
    <IsActive>true</IsActive>
  </Station>
  <Station>
    <Id>4181</Id>
    <Name>Station43</Name>
    <Longitude>35.19272408713248</Longitude>
    <Latitude>31.88884346978219</Latitude>
    <ChargeSlots>6</ChargeSlots>
    <IsActive>true</IsActive>
  </Station>
  <Station>
    <Id>3071</Id>
    <Name>Station44</Name>
    <Longitude>35.16376515490178</Longitude>
    <Latitude>31.70545486426235</Latitude>
    <ChargeSlots>8</ChargeSlots>
    <IsActive>true</IsActive>
  </Station>
  <Station>
    <Id>1609</Id>
    <Name>Station45</Name>
    <Longitude>35.191365991668484</Longitude>
    <Latitude>31.791720671808218</Latitude>
    <ChargeSlots>9</ChargeSlots>
    <IsActive>true</IsActive>
  </Station>
  <Station>
    <Id>9560</Id>
    <Name>Station46</Name>
    <Longitude>35.195341268598725</Longitude>
    <Latitude>31.767006876909644</Latitude>
    <ChargeSlots>10</ChargeSlots>
    <IsActive>true</IsActive>
  </Station>
  <Station>
    <Id>4042</Id>
    <Name>Station47</Name>
    <Longitude>35.20971727674348</Longitude>
    <Latitude>31.88812961931719</Latitude>
    <ChargeSlots>5</ChargeSlots>
    <IsActive>true</IsActive>
  </Station>
  <Station>
    <Id>6688</Id>
    <Name>Station48</Name>
    <Longitude>35.11940846676911</Longitude>
    <Latitude>31.78574034119292</Latitude>
    <ChargeSlots>5</ChargeSlots>
    <IsActive>true</IsActive>
  </Station>
  <Station>
    <Id>1636</Id>
    <Name>Station49</Name>
    <Longitude>35.15437077128066</Longitude>
    <Latitude>31.898681444580983</Latitude>
    <ChargeSlots>6</ChargeSlots>
    <IsActive>true</IsActive>
  </Station>
  <Station>
    <Id>1234</Id>
    <Name>ddddd</Name>
    <Longitude>23</Longitude>
    <Latitude>23</Latitude>
    <ChargeSlots>5</ChargeSlots>
    <IsActive>true</IsActive>
  </Station>
</ArrayOfStation>